trundlerpy/__init__.py
trundlerpy/_checkfuncions.py
trundlerpy/_params.py
trundlerpy/_product.py
trundlerpy/_retailer.py
trundlerpy-0.1.2.dist-info/METADATA
trundlerpy-0.1.2.dist-info/WHEEL
trundlerpy-0.1.2.dist-info/top_level.txt
trundlerpy-0.1.2.dist-info/RECORD
