Metadata-Version: 2.1
Name: trundlerpy
Version: 0.1.2
Summary: Trundler Python Package
Home-page: https://github.com/datawookie/trundlerpy
Author: Laura Calcagni, Andrew B. Collier
Author-email: l.calcagni@gmail.com, andrew@exegetic.biz
License: UNKNOWN
Platform: UNKNOWN
Requires-Dist: numpy (==1.18.5)
Requires-Dist: pandas (==1.0.5)
Requires-Dist: requests (==2.24.0)
